{
  "versionCode": 1025,
  "versionName": "0.1.25",
  "apkUrl": "https://github.com/timakademikmim/mim-app/releases/download/native-android-v0.1.25/MIM.APP.apk",
  "releaseNotes": "MIM App Android 0.1.25. Perbaikan tautkan akun Google.",
  "features": [
    "Login Android kini menyediakan tombol Masuk dengan Google.",
    "Profil pengguna memiliki menu Akun Google untuk menautkan akun Google.",
    "Tombol tautkan Google sekarang menampilkan proses dan pesan hasil langsung di halaman profil."
  ],
  "fixes": [
    "Memperbaiki tombol Tautkan Google yang sebelumnya bisa tidak membuka halaman Google.",
    "Sesi login diperbarui terlebih dahulu sebelum proses tautkan Google dimulai.",
    "Endpoint link Google kini meminta URL OAuth tanpa redirect internal agar dapat dibuka oleh aplikasi."
  ],
  "mandatory": true
}
